auto_checker/__init__.py
auto_checker/code_solution_checker.py
auto_checker-1.0.5.dist-info/LICENSE
auto_checker-1.0.5.dist-info/METADATA
auto_checker-1.0.5.dist-info/WHEEL
auto_checker-1.0.5.dist-info/top_level.txt
auto_checker-1.0.5.dist-info/RECORD
