Metadata-Version: 2.1
Name: auto-checker
Version: 1.0.5
Summary: A  light weight package to check the codes of candidates who interview with me.
Home-page: https://github.com/kevinscaria/auto_checker
Author: Kevin Scaria
Author-email: scariakevin1@gmail.com
License: UNKNOWN
Platform: UNKNOWN
Classifier: Programming Language :: Python :: 3
Classifier: License :: OSI Approved :: MIT License
Classifier: Operating System :: OS Independent
